tensortradesdk/__init__.py
tensortradesdk/clients/__init__.py
tensortradesdk/clients/active_listings_v_2.py
tensortradesdk/clients/async_base_client.py
tensortradesdk/clients/base_client.py
tensortradesdk/clients/base_model.py
tensortradesdk/clients/collection_data_client.py
tensortradesdk/clients/collection_data_client_async.py
tensortradesdk/clients/collection_mints.py
tensortradesdk/clients/collection_stats.py
tensortradesdk/clients/collections_stats.py
tensortradesdk/clients/enums.py
tensortradesdk/clients/exceptions.py
tensortradesdk/clients/hade_swap_active_orders.py
tensortradesdk/clients/hswap_buy_nft_tx.py
tensortradesdk/clients/hswap_sell_nft_tx.py
tensortradesdk/clients/input_types.py
tensortradesdk/clients/market_data_client.py
tensortradesdk/clients/market_data_client_async.py
tensortradesdk/clients/mint.py
tensortradesdk/clients/mint_list.py
tensortradesdk/clients/mints.py
tensortradesdk/clients/new_transaction_tv_2.py
tensortradesdk/clients/refetch_mint_metadata.py
tensortradesdk/clients/refresh_rarities.py
tensortradesdk/clients/single_collection_stats.py
tensortradesdk/clients/subscriptions_client_async.py
tensortradesdk/clients/take_bid_tx.py
tensortradesdk/clients/tcomp_bid_tx.py
tensortradesdk/clients/tcomp_bid_tx_for_collection.py
tensortradesdk/clients/tcomp_bids.py
tensortradesdk/clients/tcomp_buy_tx.py
tensortradesdk/clients/tcomp_cancel_coll_bid_tx.py
tensortradesdk/clients/tcomp_delist_tx.py
tensortradesdk/clients/tcomp_edit_bid_tx.py
tensortradesdk/clients/tcomp_edit_tx.py
tensortradesdk/clients/tcomp_list_tx.py
tensortradesdk/clients/tcomp_take_bid_tx.py
tensortradesdk/clients/tcomp_trait_bid_tx.py
tensortradesdk/clients/tensor_swap_active_orders.py
tensortradesdk/clients/transactions_client.py
tensortradesdk/clients/transactions_client_async.py
tensortradesdk/clients/tswap_buy_nft_tx.py
tensortradesdk/clients/tswap_buy_single_listing_tx.py
tensortradesdk/clients/tswap_close_pool_tx.py
tensortradesdk/clients/tswap_delist_nft_tx.py
tensortradesdk-0.1.1.dist-info/METADATA
tensortradesdk-0.1.1.dist-info/WHEEL
tensortradesdk-0.1.1.dist-info/entry_points.txt
tensortradesdk-0.1.1.dist-info/RECORD
