Metadata-Version: 2.1
Name: tensortradesdk
Version: 0.1.1
Summary: The Tensor.trade Python SDK is a Python toolkit for interfacing with the Tensor.trade API, offering easy access to trading and financial data through GraphQL queries for developers.
Author: Damjan Kuznar
Author-email: damjan.kuznar@gmail.com
Requires-Python: >=3.10,<4.0
Classifier: Programming Language :: Python :: 3
Classifier: Programming Language :: Python :: 3.10
Classifier: Programming Language :: Python :: 3.11
Classifier: Programming Language :: Python :: 3.12
Requires-Dist: graphql-core (>=3.2.0,<3.3)
Requires-Dist: httpx (>=0.23,<1.0)
Requires-Dist: pydantic (>=2.0.0,<3.0.0)
Requires-Dist: solana (>=0.30.0,<0.31.0)
Requires-Dist: tenacity (>=8.2,<9.0)
Requires-Dist: websockets (>=11.0,<12.0)
